cv2_rgb/__init__.py
cv2_rgb-1.0.0.dist-info/LICENSE
cv2_rgb-1.0.0.dist-info/METADATA
cv2_rgb-1.0.0.dist-info/WHEEL
cv2_rgb-1.0.0.dist-info/top_level.txt
cv2_rgb-1.0.0.dist-info/RECORD
