Metadata-Version: 2.1
Name: cv2-rgb
Version: 1.0.0
Summary: Python wrapper over OpenCV which by default loads images in RGB as opposed to BGR
Home-page: UNKNOWN
Author: Bartłomiej Śmietanka
License: MIT
Platform: unix
Platform: linux
Platform: osx
Platform: cygwin
Platform: win32
Classifier: Programming Language :: Python :: 3
Classifier: Programming Language :: Python :: 3 :: Only
Classifier: Programming Language :: Python :: 3.7
Classifier: Programming Language :: Python :: 3.8
Classifier: Programming Language :: Python :: 3.9
Requires-Python: >=3.7
Provides-Extra: testing
License-File: LICENSE
